Metadata-Version: 2.1
Name: bizzbuzz
Version: 0.0.6
Summary: A news aggregator service which provides users with all the latest news or ‘buzz’ about their favorite businesses.
Home-page: https://github.com/andrewbriceno/bizbuzz.git
Author: Bizz Buzzers
License: UNKNOWN
Platform: UNKNOWN
Requires-Python: >=3.5, <4
Requires-Dist: lxml
Requires-Dist: beautifulsoup4
Requires-Dist: Django
Requires-Dist: requests
